cqh_psum/__init__.py
cqh_psum/conf.py
cqh_psum/run.py
cqh_psum-0.0.8.dist-info/LICENSE
cqh_psum-0.0.8.dist-info/METADATA
cqh_psum-0.0.8.dist-info/WHEEL
cqh_psum-0.0.8.dist-info/entry_points.txt
cqh_psum-0.0.8.dist-info/top_level.txt
cqh_psum-0.0.8.dist-info/RECORD
